jsont/__init__.py
jsont/version.py
jsont/cli/__init__.py
jsont/cli/cli.py
jsont-0.0.5.dist-info/LICENSE
jsont-0.0.5.dist-info/METADATA
jsont-0.0.5.dist-info/WHEEL
jsont-0.0.5.dist-info/entry_points.txt
jsont-0.0.5.dist-info/top_level.txt
jsont-0.0.5.dist-info/RECORD
