Metadata-Version: 2.1
Name: jsont
Version: 0.0.5
Summary: JSON Transformer
Home-page: https://github.com/ivangeorgiev/jsont
Author: Ivan Georgiev
License: UNKNOWN
Platform: UNKNOWN
Classifier: Programming Language :: Python :: 3
Classifier: License :: OSI Approved :: MIT License
Classifier: Operating System :: OS Independent
Requires-Python: >=3.7
Requires-Dist: click
